[{"id":3,"shortname":"DLI","fullname":"Diseño lógico I","enrolledusercount":2,"idnumber":"","visible":1,"summary":"<p>este es el curso de diseño lógico I para los alumnos de ingeniería en computación. los alumnos deben inscribirse además en el sistema alumnos</p>","summaryformat":1,"format":"topics","showgrades":true,"lang":"","enablecompletion":true,"category":2,"progress":0,"startdate":1664247600,"enddate":1695783600},{"id":2,"shortname":"TD","fullname":"Transmisión de Datos","enrolledusercount":2,"idnumber":"","visible":1,"summary":"","summaryformat":1,"format":"topics","showgrades":true,"lang":"","enablecompletion":true,"category":2,"progress":0,"startdate":1663210800,"enddate":1694746800}]